excelReader/__init__.py
excelReader-0.0.1.dist-info/METADATA
excelReader-0.0.1.dist-info/WHEEL
excelReader-0.0.1.dist-info/top_level.txt
excelReader-0.0.1.dist-info/RECORD
